llamazure/azrest/__init__.py
llamazure/azrest/azrest.py
llamazure/azrest/models.py
llamazure/azrest/openapi.py
llamazure/azrest/openapi_info.py
llamazure/azrest/openapi_inspect.py
llamazure.azrest-0.4.0.dist-info/METADATA
llamazure.azrest-0.4.0.dist-info/WHEEL
llamazure.azrest-0.4.0.dist-info/entry_points.txt
llamazure.azrest-0.4.0.dist-info/namespace_packages.txt
llamazure.azrest-0.4.0.dist-info/top_level.txt
llamazure.azrest-0.4.0.dist-info/RECORD
