Metadata-Version: 2.1
Name: llamazure.azrest
Version: 0.4.0
Summary: Azure REST client
Author: Daniel Goldman
License: Round Robin 2.0.0
Classifier: Development Status :: 3 - Alpha
Classifier: Programming Language :: Python :: 3.9
Classifier: Programming Language :: Python :: 3.10
Classifier: Programming Language :: Python :: 3.11
Classifier: Programming Language :: Python :: 3.12
Classifier: Programming Language :: Python :: 3.13
Classifier: Topic :: Utilities
Classifier: Topic :: Internet :: Log Analysis
Requires-Python: >=3.10
Requires-Dist: click~=8.0
Requires-Dist: pydantic>=2.0
Requires-Dist: requests<3,>=2
Requires-Dist: types-requests
Provides-Extra: cli
Requires-Dist: click>8; extra == "cli"
